src/control_fsm.sv
module control_fsm (
    input  logic clk, reset_ni,
    input  logic pressed_i,
    output logic enable_o
);

    localparam IDLE  = 0;
    localparam ACCUM = 1;

    logic state, nextstate;

    always @(posedge clk or negedge reset_ni) begin
        if (!reset_ni) state <= IDLE;
        else state <= nextstate;
    end

    always @(*) begin
        case (state)
            IDLE: begin
                if (pressed_i) nextstate <= ACCUM;
                else nextstate <=IDLE;
                enable_o <= 0;
            end
            ACCUM: begin
                if (pressed_i) nextstate <= ACCUM;
                else nextstate <= IDLE;
                enable_o <= 1;
            end
            default: begin
                nextstate <= ACCUM;
                enable_o <= 0;
            end
        endcase
    end

    
endmodule

src/register.sv
module register (
    input  logic clk,
    input  logic in_i,
    output logic out_o 
);

    always @(posedge clk) begin
        out_o <= in_i;
    end
    
endmodule

src/comparator_20.sv
module comparator_20 (
    input  logic [5:0] in_i,
    output logic       valid_o,
    output logic [2:0] change_o
);

    logic [5:0] change_temp;

    always @(*) begin
        if (in_i < 20) begin 
            valid_o <= 0;
            change_temp <= 0;
        end else if (in_i == 20) begin
            valid_o <= 1;
            change_temp <= 0;
        end else if (in_i > 20) begin
            valid_o <= 1;
            change_temp <= in_i - 20;
        end else change_o <= change_o;
    end

    always @(*) begin
        case (change_temp)
            6'h0:    change_o <= 3'b000;
            6'h5:    change_o <= 3'b001;
            6'd10:   change_o <= 3'b010;
            6'd15:   change_o <= 3'b011;
            6'd20:   change_o <= 3'b100;
            default: change_o <= 3'b000;
        endcase
    end

endmodule

src/accumulator.sv
module accumulator (
    input  logic       reset_ni, enable_pi,
    input  logic [4:0] in_i,
    output logic [5:0] result_o
);

    always @(posedge enable_pi or negedge reset_ni) begin
        if (!reset_ni) result_o <= 0;
        else if (enable_pi) result_o <= result_o + in_i;
        else result_o <= result_o;
    end
    
endmodule

src/input_decoder.sv
module input_decoder (
    input  logic       nickel_i, dime_i, quarter_i,
    output             pressed_i,
    output logic [4:0] value_o
);

    assign pressed_i = nickel_i | dime_i | quarter_i;

    always @(*) begin
        if (nickel_i & (!dime_i) & (!quarter_i)) value_o <= 5;
        else if ((!nickel_i) & (dime_i) & (!quarter_i)) value_o <= 10;
        else if ((!nickel_i) & (!dime_i) & (quarter_i)) value_o <= 25;
        else value_o <= 0;
    end
    
endmodule

src/vending_machine_top.sv
module vending_machine_top (
    input  logic       clk_i,
    input  logic       reset_ni,
    input  logic       nickel_i, dime_i, quarter_i,
    output logic       soda_o,
    output logic [2:0] change_o
);

    logic pressed, reset, comp_reset, enable;
    logic [4:0] input_value;
    logic [5:0] accum_result;

    assign pressed = nickel_i | dime_i | quarter_i;
    assign reset   = reset_ni & comp_reset;

    input_decoder input_decoder_inst (
        .nickel_i (nickel_i),
        .dime_i   (dime_i),
        .quarter_i(quarter_i),
        .value_o  (input_value)
    );

    accumulator accumulator_inst (
        .reset_ni (reset),
        .enable_pi(enable),
        .in_i     (input_value),
        .result_o (accum_result)    
    );

    comparator_20 comparator_20_inst (
        .in_i    (accum_result),
        .valid_o (soda_o),
        .change_o(change_o)
    );

    register register_inst (
        .clk  (clk_i),
        .in_i (~soda_o),
        .out_o(comp_reset)
    );

    control_fsm control_fsm_inst (
        .clk      (clk_i),
        .reset_ni (reset_ni),
        .pressed_i(pressed),
        .enable_o (enable)
    );

    
endmodule

tb/vending_machine_tb.sv
`timescale 1ns/1ns

module vending_machine_tb ();

    logic       clk, rst, nickel_i, dime_i, quarter_i, soda_o;
    logic [2:0] change_o;

    vending_machine_top vending_machine_top_tb (
        .clk_i    (clk),
        .reset_ni (rst),
        .nickel_i (nickel_i),
        .dime_i   (dime_i),
        .quarter_i(quarter_i),
        .soda_o   (soda_o),
        .change_o (change_o)
    );

    initial begin
        $dumpfile("vending_machine_tb.vcd");
        $dumpvars(0,vending_machine_tb);
    end

    initial begin
        clk = 0;
        forever begin
            #5 clk = ~clk;
        end
    end

    initial begin
        rst =0;
        #2;
        rst =1;
    end

    initial begin
        nickel_i = 0;
        dime_i = 0;
        quarter_i = 0;

        #16;
        dime_i = 1;
        #10;
        dime_i = 0;
        #10;
        dime_i = 1;
        #10;
        dime_i = 0;

        #20;
        quarter_i = 1;
        #10;
        quarter_i = 0;

        #100;
        $finish();
    end
    
endmodule

sim/vending_machine_tb.vcd
$date
	Sun Sep 15 21:25:47 2024
$end
$version
	Icarus Verilog
$end
$timescale
	1ns
$end
$scope module vending_machine_tb $end
$var wire 1 ! soda_o $end
$var wire 3 " change_o [2:0] $end
$var reg 1 # clk $end
$var reg 1 $ dime_i $end
$var reg 1 % nickel_i $end
$var reg 1 & quarter_i $end
$var reg 1 ' rst $end
$scope module vending_machine_top_tb $end
$var wire 1 # clk_i $end
$var wire 1 $ dime_i $end
$var wire 1 % nickel_i $end
$var wire 1 ( pressed $end
$var wire 1 & quarter_i $end
$var wire 1 ) reset $end
$var wire 1 ' reset_ni $end
$var wire 1 ! soda_o $end
$var wire 5 * input_value [4:0] $end
$var wire 1 + enable $end
$var wire 1 , comp_reset $end
$var wire 3 - change_o [2:0] $end
$var wire 6 . accum_result [5:0] $end
$scope module accumulator_inst $end
$var wire 1 ) reset_ni $end
$var wire 5 / in_i [4:0] $end
$var wire 1 + enable_pi $end
$var reg 6 0 result_o [5:0] $end
$upscope $end
$scope module comparator_20_inst $end
$var wire 6 1 in_i [5:0] $end
$var reg 3 2 change_o [2:0] $end
$var reg 6 3 change_temp [5:0] $end
$var reg 1 ! valid_o $end
$upscope $end
$scope module control_fsm_inst $end
$var wire 1 # clk $end
$var wire 1 ( pressed_i $end
$var wire 1 ' reset_ni $end
$var reg 1 + enable_o $end
$var reg 1 4 nextstate $end
$var reg 1 5 state $end
$upscope $end
$scope module input_decoder_inst $end
$var wire 1 $ dime_i $end
$var wire 1 % nickel_i $end
$var wire 1 6 pressed_i $end
$var wire 1 & quarter_i $end
$var reg 5 7 value_o [4:0] $end
$upscope $end
$scope module register_inst $end
$var wire 1 # clk $end
$var wire 1 8 in_i $end
$var reg 1 , out_o $end
$upscope $end
$upscope $end
$upscope $end
$enddefinitions $end
#0
$dumpvars
18
b0 7
06
05
04
b0 3
b0 2
b0 1
b0 0
b0 /
b0 .
b0 -
x,
0+
b0 *
0)
0(
0'
0&
0%
0$
0#
b0 "
0!
$end
#2
x)
1'
#5
1)
1,
1#
#10
0#
#15
1#
#16
14
b1010 *
b1010 /
b1010 7
1(
16
1$
#20
0#
#25
b1010 .
b1010 0
b1010 1
1+
15
1#
#26
04
b0 *
b0 /
b0 7
0(
06
0$
#30
0#
#35
0+
05
1#
#36
14
b1010 *
b1010 /
b1010 7
1(
16
1$
#40
0#
#45
08
1!
b10100 .
b10100 0
b10100 1
1+
15
1#
#46
04
b0 *
b0 /
b0 7
0(
06
0$
#50
0#
#55
18
0!
b0 .
b0 0
b0 1
0+
0)
05
0,
1#
#60
0#
#65
1)
1,
1#
#66
14
b11001 *
b11001 /
b11001 7
1(
16
1&
#70
0#
#75
b1 "
b1 -
b1 2
08
b101 3
1!
b11001 .
b11001 0
b11001 1
1+
15
1#
#76
04
b0 *
b0 /
b0 7
0(
06
0&
#80
0#
#85
b0 "
b0 -
b0 2
18
b0 3
0!
b0 .
b0 0
b0 1
0+
0)
05
0,
1#
#90
0#
#95
1)
1,
1#
